{
  "searchResults": [
    {
      "search": false
    },
    {
      "search": false
    },
    {
      "search": false
    },
    {
      "search": false
    },
    {
      "search": false
    },
    {
      "search": false
    },
    {
      "search": false
    },
    {
      "search": false
    },
    {
      "search": false
    },
    {
      "search": false
    },
    {
      "search": false
    },
    {
      "search": false
    },
    {
      "search": false
    },
    {
      "search": false
    },
    {
      "search": false
    }
  ]
}